{
  "numberplates": [
    {
      "name": "Tomas",
      "surname": "Adomavicius",
      "numberPlate": "DAB919",
      "id": 1
    },
    {
      "name": "Rokas",
      "surname": "Jonius",
      "numberPlate": "TEL123",
      "id": 2
    },
    {
      "name": "Evaldas",
      "surname": "Darantavicius",
      "numberPlate": "NAR314",
      "id": 3
    },
    {
      "name": "Kamile",
      "surname": "Urbanovic",
      "numberPlate": "MEN947",
      "id": 4
    },
    {
      "name": "Tomas ",
      "surname": "Pilius",
      "numberPlate": "BOL749",
      "id": 5
    },
    {
      "name": "Donatas",
      "surname": "Stonys",
      "numberPlate": " RPO395",
      "id": 6
    },
    {
      "name": "Rusne",
      "surname": "Donyte",
      "numberPlate": "ATO858",
      "id": 7
    },
    {
      "name": "Rokas",
      "surname": "Rokinis",
      "numberPlate": "OEP185",
      "id": 8
    },
    {
      "name": "Ponas",
      "surname": "Bynas",
      "numberPlate": "ASD121",
      "id": 9
    }
  ]
}